_nxlu/__init__.py
_nxlu/config.py
_nxlu/enums.py
_nxlu/info.py
_nxlu/logging.py
nxlu/__init__.py
nxlu/_version.py
nxlu/config.py
nxlu/constants.py
nxlu/exceptions.py
nxlu/getters.py
nxlu/io.py
nxlu/core/__init__.py
nxlu/core/base.py
nxlu/core/factory.py
nxlu/core/interface.py
nxlu/core/manager.py
nxlu/data/__init__.py
nxlu/data/algorithm_docs.json
nxlu/data/algorithm_encyclopedia.json
nxlu/data/graph_theory_corpus.txt
nxlu/data/rag_documents.jsonl
nxlu/explanation/__init__.py
nxlu/explanation/classify.py
nxlu/explanation/corpus.py
nxlu/explanation/entities.py
nxlu/explanation/explain.py
nxlu/explanation/interrogate.py
nxlu/explanation/rag.py
nxlu/processing/__init__.py
nxlu/processing/analyze.py
nxlu/processing/community.py
nxlu/processing/embed.py
nxlu/processing/optimize.py
nxlu/processing/paths.py
nxlu/processing/preprocess.py
nxlu/processing/search.py
nxlu/processing/subgraph.py
nxlu/processing/summarize.py
nxlu/processing/tests/__init__.py
nxlu/processing/tests/test_analyze.py
nxlu/processing/tests/test_community.py
nxlu/processing/tests/test_embed.py
nxlu/processing/tests/test_preprocess.py
nxlu/processing/tests/test_search.py
nxlu/processing/tests/test_summarize.py
nxlu/utils/__init__.py
nxlu/utils/control.py
nxlu/utils/data.py
nxlu/utils/log.py
nxlu/utils/misc.py
nxlu/utils/tests/__init__.py
nxlu/utils/tests/test_control.py
nxlu/utils/tests/test_misc.py
nxlu-0.1.54.dist-info/LICENSE
nxlu-0.1.54.dist-info/METADATA
nxlu-0.1.54.dist-info/WHEEL
nxlu-0.1.54.dist-info/entry_points.txt
nxlu-0.1.54.dist-info/top_level.txt
nxlu-0.1.54.dist-info/RECORD
