Metadata-Version: 2.1
Name: nxlu
Version: 0.1.54
Summary: Natural Language Understanding of Network Topology
Author-email: Derek Alexander <dpysalexander@example.com>
Keywords: networkx,graph,network,algorithm,llm
Platform: Linux
Platform: Mac OSX
Platform: Windows
Platform: Unix
Classifier: Intended Audience :: Developers
Classifier: Intended Audience :: Science/Research
Classifier: Operating System :: OS Independent
Classifier: Programming Language :: Python :: 3
Classifier: Programming Language :: Python :: 3.10
Classifier: Programming Language :: Python :: 3.11
Classifier: Programming Language :: Python :: 3.12
Classifier: Programming Language :: Python :: 3 :: Only
Requires-Python: >=3.10
License-File: LICENSE
Requires-Dist: numpy>=1.26
Requires-Dist: networkx>=3.3
Requires-Dist: scipy>=1.13
Requires-Dist: psutil>=5.9
Requires-Dist: transformers>=4.45
Requires-Dist: torch>=2.2
Requires-Dist: sentence-transformers>=3.1
Requires-Dist: huggingface-hub>=0.24
Requires-Dist: langchain>=0.3.2
Requires-Dist: langchain_openai>=0.2
Requires-Dist: langchain_community>=0.3
Requires-Dist: langchain-ollama>=0.2
Requires-Dist: langchain-anthropic>=0.2
Requires-Dist: pydantic>=2.8
Requires-Dist: setuptools>=75.1
Requires-Dist: faiss-cpu>=1.9.0
Requires-Dist: nest-asyncio>=1.6
Requires-Dist: graspologic-native>=1.2.1
Provides-Extra: llamaindex
Requires-Dist: llama-index>=0.11; extra == "llamaindex"
Requires-Dist: llama-index-llms-anthropic>=0.3; extra == "llamaindex"
Requires-Dist: llama-index-llms-openai>=0.2; extra == "llamaindex"
Requires-Dist: llama-index-llms-ollama>=0.3; extra == "llamaindex"
Requires-Dist: llama-index-embeddings-huggingface>=0.3.1; extra == "llamaindex"
Provides-Extra: dev
Requires-Dist: nltk>=3.2; extra == "dev"
Requires-Dist: neo4j>=5.23.1; extra == "dev"
Provides-Extra: test
Requires-Dist: pre-commit>=3.8.0; extra == "test"
Requires-Dist: pre-commit-hooks>=5.0.0; extra == "test"
Requires-Dist: black>=22.6.0; extra == "test"
Requires-Dist: ruff>=0.6.9; extra == "test"
Requires-Dist: pytest-sugar>=0.9.3; extra == "test"
Requires-Dist: pytest>=7.2; extra == "test"
Requires-Dist: pytest-cov>=2.7.1; extra == "test"
Requires-Dist: pytest-split>=0.7.0; extra == "test"
Requires-Dist: pytest-xdist>=1.32.0; extra == "test"
Requires-Dist: pytest-metadata>=2.0.2; extra == "test"
Requires-Dist: pytest-env>=1.1.5; extra == "test"
Requires-Dist: coverage>=7.6.1; extra == "test"
Requires-Dist: build>=1.2.2; extra == "test"
Requires-Dist: isort>=5.13.2; extra == "test"
Provides-Extra: doc
Requires-Dist: setuptools>=45.0.0; extra == "doc"
Requires-Dist: pydata-sphinx-theme==0.15.4; extra == "doc"
Requires-Dist: furo==2024.8.6; extra == "doc"
Requires-Dist: sphinxcontrib-apidoc~=0.3.0; extra == "doc"
Requires-Dist: sphinx-autobuild==2024.10.3; extra == "doc"
Requires-Dist: sphinxcontrib-napoleon; extra == "doc"
Requires-Dist: myst_parser>=4.0.0; extra == "doc"
Requires-Dist: sphinx_autodoc_typehints>=2.4.4; extra == "doc"
Requires-Dist: sphinx<9.0.0,>=8.0.2; extra == "doc"
